perplexity_mcp/__init__.py
perplexity_mcp/__main__.py
perplexity_mcp/run.py
perplexity_mcp/server.py
perplexity_mcp/version.py
perplexity_mcp_server-0.2.3.dist-info/METADATA
perplexity_mcp_server-0.2.3.dist-info/WHEEL
perplexity_mcp_server-0.2.3.dist-info/entry_points.txt
perplexity_mcp_server-0.2.3.dist-info/licenses/LICENSE
perplexity_mcp_server-0.2.3.dist-info/RECORD
