Metadata-Version: 2.4
Name: perplexity-mcp-server
Version: 0.2.3
Summary: Perplexity MCP Server
License-File: LICENSE
Requires-Python: >=3.11
Requires-Dist: aiohttp
Requires-Dist: certifi
Requires-Dist: mcp>=1.0.2
Requires-Dist: pydantic
